edfi_lms_extractor_lib/__init__.py
edfi_lms_extractor_lib/api/__init__.py
edfi_lms_extractor_lib/api/resource_sync.py
edfi_lms_extractor_lib/csv_generation/__init__.py
edfi_lms_extractor_lib/csv_generation/write.py
edfi_lms_extractor_lib/helpers/__init__.py
edfi_lms_extractor_lib/helpers/decorators.py
edfi_lms_extractor_lib/py.typed
edfi_lms_extractor_lib-1.1.6.dist-info/METADATA
edfi_lms_extractor_lib-1.1.6.dist-info/WHEEL
edfi_lms_extractor_lib-1.1.6.dist-info/RECORD
