Metadata-Version: 2.1
Name: edfi-lms-extractor-lib
Version: 1.1.6
Summary: Shared functions library for Ed-Fi LMS Extractor projects
Home-page: https://docs.ed-fi.org/getting-started/edfi-exchange/technology/ed-fi-lms-toolkit
License: Apache-2.0
Author: Ed-Fi Alliance, LLC, and contributors
Requires-Python: >=3.9,<4.0
Classifier: License :: OSI Approved :: Apache Software License
Classifier: Programming Language :: Python :: 3
Classifier: Programming Language :: Python :: 3.9
Classifier: Programming Language :: Python :: 3.10
Classifier: Programming Language :: Python :: 3.11
Classifier: Programming Language :: Python :: 3.12
Requires-Dist: SQLAlchemy (>=1,<2)
Requires-Dist: numpy (>=1,<2)
Requires-Dist: pandas (<2.0.0)
Requires-Dist: xxhash (>=2.0.0,<3.0.0)
Project-URL: Repository, https://github.com/Ed-Fi-Exchange-OSS/LMS-Toolkit
